{"data":{"temperature":"23","feels_like":"24","wind_speed":"20.2","wind_degree":"10","humidity":"61","visibility":"10","pressure":"1019","code":"116","city":"Funchal","forecast":[{"date":"2019-10-10","max":"19","min":"9","rain":"20","rain_unit":"%","code":"176","sunrise":"08:08 AM","sunset":"07:41 PM","moonrise":"06:22 PM","moonset":"04:55 AM","uvIndex":""},{"date":"2019-10-11","max":"17","min":"15","rain":"0","rain_unit":"%","code":"116","sunrise":"08:08 AM","sunset":"07:40 PM","moonrise":"06:52 PM","moonset":"05:50 AM","uvIndex":""},{"date":"2019-10-12","max":"18","min":"14","rain":"0","rain_unit":"%","code":"116","sunrise":"08:09 AM","sunset":"07:39 PM","moonrise":"07:22 PM","moonset":"06:43 AM","uvIndex":""},{"date":"2019-10-13","max":"16","min":"8","rain":"100","rain_unit":"%","code":"302","sunrise":"08:10 AM","sunset":"07:38 PM","moonrise":"07:51 PM","moonset":"07:38 AM","uvIndex":""},{"date":"2019-10-14","max":"15","min":"9","rain":"100","rain_unit":"%","code":"176","sunrise":"08:10 AM","sunset":"07:37 PM","moonrise":"08:20 PM","moonset":"08:32 AM","uvIndex":""},{"date":"2019-10-15","max":"16","min":"8","rain":"100","rain_unit":"%","code":"176","sunrise":"08:11 AM","sunset":"07:35 PM","moonrise":"08:52 PM","moonset":"09:28 AM","uvIndex":""},{"date":"2019-10-16","max":"15","min":"6","rain":"100","rain_unit":"%","code":"293","sunrise":"08:12 AM","sunset":"07:34 PM","moonrise":"09:27 PM","moonset":"10:25 AM","uvIndex":""}],"hourly":[{"hour":"15:00","temperature":"17","wind_speed":"13.3","wind_degree":"43","code":"116","rain":"0","rain_unit":"%"},{"hour":"16:00","temperature":"16","wind_speed":"13.1","wind_degree":"41","code":"116","rain":"0","rain_unit":"%"},{"hour":"17:00","temperature":"15","wind_speed":"12.8","wind_degree":"39","code":"116","rain":"0","rain_unit":"%"},{"hour":"18:00","temperature":"14","wind_speed":"12.6","wind_degree":"37","code":"116","rain":"0","rain_unit":"%"},{"hour":"19:00","temperature":"13","wind_speed":"12.4","wind_degree":"36","code":"116","rain":"0","rain_unit":"%"},{"hour":"20:00","temperature":"12","wind_speed":"12.1","wind_degree":"34","code":"116","rain":"0","rain_unit":"%"},{"hour":"21:00","temperature":"10","wind_speed":"11.9","wind_degree":"33","code":"116","rain":"0","rain_unit":"%"},{"hour":"22:00","temperature":"12","wind_speed":"11.5","wind_degree":"31","code":"116","rain":"0","rain_unit":"%"},{"hour":"23:00","temperature":"13","wind_speed":"11.2","wind_degree":"30","code":"116","rain":"0","rain_unit":"%"}]}}